jdbcer.py
jdbcer-0.0.2.dist-info/METADATA
jdbcer-0.0.2.dist-info/WHEEL
jdbcer-0.0.2.dist-info/entry_points.txt
jdbcer-0.0.2.dist-info/top_level.txt
jdbcer-0.0.2.dist-info/RECORD
